ivoire/__init__.py
ivoire/__main__.py
ivoire/load.py
ivoire/manager.py
ivoire/result.py
ivoire/run.py
ivoire/standalone.py
ivoire/transform.py
ivoire/spec/__init__.py
ivoire/spec/util.py
ivoire/spec/unit/__init__.py
ivoire/spec/unit/context_manager_spec.py
ivoire/spec/unit/context_spec.py
ivoire/spec/unit/describe_spec.py
ivoire/spec/unit/example_spec.py
ivoire/spec/unit/load_spec.py
ivoire/spec/unit/result_spec.py
ivoire/spec/unit/run_spec.py
ivoire/spec/unit/transform_spec.py
ivoire/tests/__init__.py
ivoire/tests/test_result.py
ivoire/tests/test_standalone.py
ivoire/tests/test_transform.py
ivoire/tests/util.py
ivoire-0.4.0.dist-info/METADATA
ivoire-0.4.0.dist-info/WHEEL
ivoire-0.4.0.dist-info/entry_points.txt
ivoire-0.4.0.dist-info/licenses/COPYING
ivoire-0.4.0.dist-info/RECORD
