Metadata-Version: 2.1
Name: ivoire
Version: 0.4.0
Summary: A simple RSpec-like testing framework.
Project-URL: Homepage, https://github.com/Julian/Ivoire
Project-URL: Issues, https://github.com/Julian/Ivoire/issues/
Project-URL: Funding, https://github.com/sponsors/Julian
Project-URL: Source, https://github.com/Julian/Ivoire
Author: Julian Berman
Author-email: Julian+Ivoire@GrayVines.com
License: MIT
License-File: COPYING
Classifier: Development Status :: 4 - Beta
Classifier: Intended Audience :: Developers
Classifier: License :: OSI Approved :: MIT License
Classifier: Operating System :: OS Independent
Classifier: Programming Language :: Python
Classifier: Programming Language :: Python :: 3
Classifier: Programming Language :: Python :: 3.8
Classifier: Programming Language :: Python :: 3.9
Classifier: Programming Language :: Python :: 3.10
Classifier: Programming Language :: Python :: 3.11
Classifier: Programming Language :: Python :: Implementation :: CPython
Classifier: Programming Language :: Python :: Implementation :: PyPy
Requires-Python: >=3.8
